kusa_ads_protobuf/__init__.py
kusa_ads_protobuf/openads/__init__.py
kusa_ads_protobuf/openads/proto/__init__.py
kusa_ads_protobuf/openads/proto/application/__init__.py
kusa_ads_protobuf/openads/proto/application/abstract_config_pb2.py
kusa_ads_protobuf/openads/proto/application/application_config_pb2.py
kusa_ads_protobuf/openads/proto/application/comm_config_pb2.py
kusa_ads_protobuf/openads/proto/application/date_machine_config_pb2.py
kusa_ads_protobuf/openads/proto/application/scheduler_config_pb2.py
kusa_ads_protobuf/openads/proto/application/stage_config_pb2.py
kusa_ads_protobuf/openads/proto/audio/__init__.py
kusa_ads_protobuf/openads/proto/audio/audio_common_pb2.py
kusa_ads_protobuf/openads/proto/audio/audio_conf_pb2.py
kusa_ads_protobuf/openads/proto/audio/audio_event_pb2.py
kusa_ads_protobuf/openads/proto/audio/audio_pb2.py
kusa_ads_protobuf/openads/proto/canbus/__init__.py
kusa_ads_protobuf/openads/proto/canbus/asensing_pb2.py
kusa_ads_protobuf/openads/proto/canbus/canbus_conf_pb2.py
kusa_ads_protobuf/openads/proto/canbus/cantest_pb2.py
kusa_ads_protobuf/openads/proto/canbus/ch_pb2.py
kusa_ads_protobuf/openads/proto/canbus/chassis_detail_pb2.py
kusa_ads_protobuf/openads/proto/canbus/chassis_pb2.py
kusa_ads_protobuf/openads/proto/canbus/delphi_pb2.py
kusa_ads_protobuf/openads/proto/canbus/delphi_radar_conf_pb2.py
kusa_ads_protobuf/openads/proto/canbus/devkit_pb2.py
kusa_ads_protobuf/openads/proto/canbus/ge3_pb2.py
kusa_ads_protobuf/openads/proto/canbus/lexus_pb2.py
kusa_ads_protobuf/openads/proto/canbus/mnai_1t_1gen_pb2.py
kusa_ads_protobuf/openads/proto/canbus/neolix_edu_pb2.py
kusa_ads_protobuf/openads/proto/canbus/newencher_pb2.py
kusa_ads_protobuf/openads/proto/canbus/transit_pb2.py
kusa_ads_protobuf/openads/proto/canbus/ultrasonic_radar_pb2.py
kusa_ads_protobuf/openads/proto/canbus/vehicle_parameter_pb2.py
kusa_ads_protobuf/openads/proto/canbus/wey_pb2.py
kusa_ads_protobuf/openads/proto/canbus/zhongyun_pb2.py
kusa_ads_protobuf-1.2.0.dist-info/METADATA
kusa_ads_protobuf-1.2.0.dist-info/WHEEL
kusa_ads_protobuf-1.2.0.dist-info/top_level.txt
kusa_ads_protobuf-1.2.0.dist-info/RECORD
