Metadata-Version: 2.1
Name: kusa-ads-protobuf
Version: 1.2.0
Summary: A package for KUSA ADS protobuf definitions
Home-page: https://github.com/kusa-ads/kusa-ads-protobuf
Author: KUSA ADS Team
Author-email: hai.l@kusaauto.com
Classifier: Development Status :: 3 - Alpha
Classifier: License :: OSI Approved :: MIT License
Classifier: Programming Language :: Python :: 3
Requires-Dist: requests
